keywordsai_instrumentation_langfuse/__init__.py
keywordsai_instrumentation_langfuse/instrumentor.py
keywordsai_instrumentation_langfuse-0.1.1.dist-info/METADATA
keywordsai_instrumentation_langfuse-0.1.1.dist-info/WHEEL
keywordsai_instrumentation_langfuse-0.1.1.dist-info/entry_points.txt
keywordsai_instrumentation_langfuse-0.1.1.dist-info/RECORD
