Metadata-Version: 2.1
Name: keywordsai-instrumentation-langfuse
Version: 0.1.1
Summary: OTEL-compliant instrumentation for Langfuse to send traces to Keywords AI
License: Apache-2.0
Author: Keywords AI
Author-email: support@keywordsai.co
Requires-Python: >=3.10,<4.0
Classifier: License :: OSI Approved :: Apache Software License
Classifier: Programming Language :: Python :: 3
Classifier: Programming Language :: Python :: 3.10
Classifier: Programming Language :: Python :: 3.11
Classifier: Programming Language :: Python :: 3.12
Requires-Dist: httpx (>=0.28.1,<0.29.0)
Requires-Dist: langfuse (>=3.12.0,<4.0.0)
Requires-Dist: opentelemetry-api (>=1.39.1,<2.0.0)
Requires-Dist: opentelemetry-instrumentation (>=0.60b1,<0.61)
Requires-Dist: opentelemetry-sdk (>=1.39.1,<2.0.0)
Requires-Dist: requests (>=2.32.5,<3.0.0)
